MANIFEST.in
README.rst
setup.py
appearance/__init__.py
appearance/admin.py
appearance/fields.py
appearance/models.py
appearance/widgets.py
appearance/migrations/0001_initial.py
appearance/migrations/0002_auto_20160918_2121.py
appearance/migrations/__init__.py
appearance/static/colorfield/css/colorpicker.css
appearance/static/colorfield/css/layout.css
appearance/static/colorfield/images/Thumbs.db
appearance/static/colorfield/images/blank.gif
appearance/static/colorfield/images/colorpicker_background.png
appearance/static/colorfield/images/colorpicker_hex.png
appearance/static/colorfield/images/colorpicker_hsb_b.png
appearance/static/colorfield/images/colorpicker_hsb_h.png
appearance/static/colorfield/images/colorpicker_hsb_s.png
appearance/static/colorfield/images/colorpicker_indic.gif
appearance/static/colorfield/images/colorpicker_overlay.png
appearance/static/colorfield/images/colorpicker_rgb_b.png
appearance/static/colorfield/images/colorpicker_rgb_g.png
appearance/static/colorfield/images/colorpicker_rgb_r.png
appearance/static/colorfield/images/colorpicker_select.gif
appearance/static/colorfield/images/colorpicker_submit.png
appearance/static/colorfield/images/custom_background.png
appearance/static/colorfield/images/custom_hex.png
appearance/static/colorfield/images/custom_hsb_b.png
appearance/static/colorfield/images/custom_hsb_h.png
appearance/static/colorfield/images/custom_hsb_s.png
appearance/static/colorfield/images/custom_indic.gif
appearance/static/colorfield/images/custom_rgb_b.png
appearance/static/colorfield/images/custom_rgb_g.png
appearance/static/colorfield/images/custom_rgb_r.png
appearance/static/colorfield/images/custom_submit.png
appearance/static/colorfield/images/select.png
appearance/static/colorfield/images/select2.png
appearance/static/colorfield/images/slider.png
appearance/static/colorfield/js/colorpicker.js
appearance/static/colorfield/js/eye.js
appearance/static/colorfield/js/jquery.js
appearance/static/colorfield/js/layout.js
django_exchange_themes.egg-info/PKG-INFO
django_exchange_themes.egg-info/SOURCES.txt
django_exchange_themes.egg-info/dependency_links.txt
django_exchange_themes.egg-info/not-zip-safe
django_exchange_themes.egg-info/requires.txt
django_exchange_themes.egg-info/top_level.txt