Metadata-Version: 1.1
Name: django-exchange-themes
Version: 1.0.3
Summary: A Django Application for Boundless Exchange Themes.
Home-page: https://github.com/boundlessgeo/django-exchange-themes
Author: Boundless Spatial, Maxime Haineault (django-colorfield)
Author-email: contact@boundlessgeo.com
License: BSD
Download-URL: https://github.com/boundlessgeo/django-exchange-themes
Platform: UNKNOWN
Classifier: Topic :: Documentation :: Sphinx
Classifier: Topic :: Software Development :: Documentation
Classifier: Intended Audience :: End Users/Desktop
Classifier: Intended Audience :: System Administrators
Classifier: Environment :: Web Environment
Classifier: License :: OSI Approved :: BSD License
Classifier: Development Status :: 3 - Alpha
Classifier: Operating System :: OS Independent
Classifier: Programming Language :: Python :: 2.7
Classifier: Framework :: Django :: 1.8
